ShazamAPI/__init__.py
ShazamAPI/algorithm.py
ShazamAPI/api.py
ShazamAPI/signature_format.py
ShazamAPI-0.0.2.dist-info/METADATA
ShazamAPI-0.0.2.dist-info/WHEEL
ShazamAPI-0.0.2.dist-info/top_level.txt
ShazamAPI-0.0.2.dist-info/RECORD
