Metadata-Version: 2.1
Name: ShazamAPI
Version: 0.0.2
Summary: Fully reverse engeenired shazam api
Home-page: https://github.com/Numenorean/ShazamAPI
Author: Numenorean
Author-email: author@example.com
License: UNKNOWN
Platform: UNKNOWN
Requires-Python: >=3.6
